Metadata-Version: 2.1
Name: muhammad-hassan
Version: 1.0
Summary: Gaussian distributions and Binomial distribution
Home-page: UNKNOWN
Author: Muhammad Hassan
License: UNKNOWN
Platform: UNKNOWN
